[{"name":"Mad Catz","shortname":"MCZ","codename":"MAD CATZ","logo":null,"twitter":"madcatz","website":"http://madcatz.com/"},{"name":"Evil Geniuses","shortname":"EG","codename":"EVIL GENIUSES","logo":null,"twitter":"EvilGeniuses","website":"http://evilgeniuses.gg/"},{"name":"Avermedia","shortname":"AVM","codename":"AVERMEDIA","logo":null,"twitter":"AVerMediaGaming","website":"http://gamerzone.avermedia.com/"},{"name":"Team Razer","shortname":"RZR","codename":"TEAM RAZER","logo":null,"twitter":"TeamRazer","website":"http://www.razerzone.com/team"},{"name":"Team HORI","shortname":"HORI","codename":"TEAM HORI","logo":null,"twitter":"Team__Hori","website":"http://stores.horiusa.com/"},{"name":"RaGe","shortname":"RaGe","codename":"RAGE","logo":null,"twitter":"RaGeTeam1","website":"https://t.co/G1xdOnFtcC"},{"name":"Empire Arcadia","shortname":"EMP","codename":"EMPIRE ARCADIA","logo":null,"twitter":"EmpireArcadia","website":"http://www.empirearcadia.com/"}]